gene_finder/__init__.py
gene_finder/option_handling.py
gene_finder/orffinder.py
gene_finder/output_writers.py
gene_finder/parsers.py
gene_finder/pipeline.py
gene_finder/steps.py
gene_finder/utils.py
operon_analyzer/__init__.py
operon_analyzer/analyze.py
operon_analyzer/genes.py
operon_analyzer/load.py
operon_analyzer/overview.py
operon_analyzer/parse.py
operon_analyzer/piler_parse.py
operon_analyzer/reannotation.py
operon_analyzer/repeat_finder.py
operon_analyzer/rules.py
operon_analyzer/spacers.py
operon_analyzer/visualize.py
opfi-0.1.2.dist-info/LICENSE
opfi-0.1.2.dist-info/METADATA
opfi-0.1.2.dist-info/WHEEL
opfi-0.1.2.dist-info/top_level.txt
opfi-0.1.2.dist-info/RECORD
