Metadata-Version: 2.1
Name: opfi
Version: 0.1.2
Summary: A package for discovery, annotation, and analysis of gene clusters in genomics or metagenomics datasets.
Home-page: https://github.com/wilkelab/Opfi
Author: Alexis M Hill, James Rybarski
Author-email: alexismhill3@gmail.com
License: UNKNOWN
Platform: UNKNOWN
Classifier: Programming Language :: Python :: 3
Classifier: License :: OSI Approved :: MIT License
Classifier: Operating System :: OS Independent
Requires-Python: >=3.6
Requires-Dist: PyYAML (==5.4)
Requires-Dist: biopython (==1.76)
Requires-Dist: dna-features-viewer (==3.0.1)
Requires-Dist: hypothesis (==5.1.1)
Requires-Dist: matplotlib (==3.2.1)
Requires-Dist: more-itertools (==8.4.0)
Requires-Dist: parasail (==1.2)
Requires-Dist: pytest (==5.3.2)
